README.md
setup.py
ophion/__init__.py
ophion/ophion.py
ophion.egg-info/PKG-INFO
ophion.egg-info/SOURCES.txt
ophion.egg-info/dependency_links.txt
ophion.egg-info/top_level.txt