Metadata-Version: 1.2
Name: ophion
Version: 0.0.6
Summary: A Graph Database client library
Home-page: https://github.com/bmeg/ophion
Author: BMEG/OHSU
Author-email: kellrott@gmail.com
License: UNKNOWN
Keywords: client,graph,database
Platform: UNKNOWN
Classifier: Development Status :: 3 - Alpha
Classifier: Intended Audience :: Developers
Classifier: Natural Language :: English
Classifier: Topic :: Software Development :: Libraries
Classifier: Programming Language :: Python :: 2.7
Requires-Python: >=2.6, <3
